<annotation>
  <folder>frame</folder>
  <filename>008964.jpg</filename>
  <source>
    <database>Unknown</database>
    <annotation>Unknown</annotation>
    <image>Unknown</image>
  </source>
  <size>
    <width>300</width>
    <height>300</height>
    <depth />
  </size>
  <segmented>0</segmented>
  <object>
  <name>Label</name>
  <occluded>0</occluded>
  <truncated>0</truncated>
  <difficult>0</difficult>
  <pose>Unspecified</pose>
  <bndbox>
    <xmin>170.2054</xmin>
    <ymin>59.1861</ymin>
    <xmax>186.8687</xmax>
    <ymax>133.8042</ymax>
  </bndbox>
  <attributes>
    <attribute>
      <name>track_id</name>
      <value>0</value>
    </attribute>
    <attribute>
      <name>keyframe</name>
      <value>True</value>
    </attribute>
  </attributes>
</object>
<object>
  <name>Pliers</name>
  <occluded>0</occluded>
  <truncated>0</truncated>
  <difficult>0</difficult>
  <pose>Unspecified</pose>
  <bndbox>
    <xmin>133.3571</xmin>
    <ymin>124.3291</ymin>
    <xmax>183.9844</xmax>
    <ymax>172.8944</ymax>
  </bndbox>
  <attributes>
    <attribute>
      <name>track_id</name>
      <value>1</value>
    </attribute>
    <attribute>
      <name>keyframe</name>
      <value>True</value>
    </attribute>
  </attributes>
</object>
</annotation>